{"type":"mc","text":"On the whole, how satisfying to you was the course for which you're using this app?  Your teacher will NOT see your answer to this question.","questionId":"sec_2","required":false,"followupPart":false,"choices":["Not at all satisfying","Not very satisfying","Somewhat satisfying","Very satisfying","Extremely satisfying"],"extremes":false,"hover":false,"multi":false,"followups":[{"type":"fill","text":"Please explain your answer","questionId":"sec_2_followups0","required":true,"followupPart":true,"choices":false,"extremes":false,"hover":false,"multi":false,"followups":false,"complete":false,"answer":false,"dependant":[0,1,2,3,4]}],"complete":true,"answer":"optional"}